{
	"configurations" : 
	[
		{
			"directories" : 
			[
				{
					"build" : ".",
					"jsonFile" : "directory-.-Debug-f5ebdc15457944623624.json",
					"minimumCMakeVersion" : 
					{
						"string" : "3.29"
					},
					"projectIndex" : 0,
					"source" : ".",
					"targetIndexes" : 
					[
						0
					]
				}
			],
			"name" : "Debug",
			"projects" : 
			[
				{
					"directoryIndexes" : 
					[
						0
					],
					"name" : "pp13",
					"targetIndexes" : 
					[
						0
					]
				}
			],
			"targets" : 
			[
				{
					"directoryIndex" : 0,
					"id" : "pp13::@6890427a1f51a3e7e1df",
					"jsonFile" : "target-pp13-Debug-191fbc91c5f35d833ff1.json",
					"name" : "pp13",
					"projectIndex" : 0
				}
			]
		}
	],
	"kind" : "codemodel",
	"paths" : 
	{
		"build" : "/Users/nick/Desktop/C++/Chapter_6/pp13/cmake-build-debug",
		"source" : "/Users/nick/Desktop/C++/Chapter_6/pp13"
	},
	"version" : 
	{
		"major" : 2,
		"minor" : 7
	}
}
